geospatial_lib/__init__.py
geospatial_lib/core/__init__.py
geospatial_lib/core/core.py
geospatial_lib/core/logger.py
geospatial_lib/db/__init__.py
geospatial_lib/db/pandas_handler.py
geospatial_lib/db/pg_core.py
geospatial_lib/db/pg_handler.py
geospatial_lib/db/poetry.md
geospatial_lib/main.py
geospatial_lib/misc/__init__.py
geospatial_lib/misc/extraction.py
geospatial_lib/misc/gridding.py
geospatial_lib/misc/helpers.py
geospatial_lib/misc/processing.py
geospatial_lib-0.42.0.dist-info/LICENSE
geospatial_lib-0.42.0.dist-info/WHEEL
geospatial_lib-0.42.0.dist-info/METADATA
geospatial_lib-0.42.0.dist-info/RECORD
