Metadata-Version: 2.1
Name: geospatial-lib
Version: 0.42.0
Summary: A library with some geo functions
License: GPL3
Author: amauryval
Author-email: amauryval@gmail.com
Requires-Python: ==3.11.0
Classifier: License :: Other/Proprietary License
Classifier: Programming Language :: Python :: 3
Requires-Dist: GeoAlchemy2 (>=0.13.1,<0.14.0)
Requires-Dist: SQLAlchemy (>=2.0.4,<3.0.0)
Requires-Dist: SQLAlchemy-Utils (>=0.40.0,<0.41.0)
Requires-Dist: geopandas (>=0.12.2,<0.13.0)
Requires-Dist: psycopg2-binary (>=2.9.6,<3.0.0)
Requires-Dist: setuptools (>=67.6.1,<68.0.0)
Requires-Dist: xlrd (>=2.0.1,<3.0.0)
